drimage/__init__.py
drimage/__main__.py
drimage/commands.py
drimage/constants.py
drimage/functions.py
drimg/__init__.py
drimg/__main__.py
drimg/commands.py
drimg/constants.py
drimg/functions.py
drimg-0.0.2.dist-info/LICENSE
drimg-0.0.2.dist-info/METADATA
drimg-0.0.2.dist-info/WHEEL
drimg-0.0.2.dist-info/entry_points.txt
drimg-0.0.2.dist-info/top_level.txt
drimg-0.0.2.dist-info/RECORD
