Metadata-Version: 2.1
Name: drimg
Version: 0.0.2
Summary: drawable image creator
Home-page: https://github.com/hojjat-faryabi/drawable_image
Author: hojjat-faryabi
Author-email: hojjat.faryabi@gmail.com
License: MIT
Keywords: image,drawable,android,android-studio,drimg
Platform: UNKNOWN
Classifier: Development Status :: 3 - Alpha
Classifier: Intended Audience :: Developers
Classifier: License :: OSI Approved :: MIT License
Classifier: Programming Language :: Python :: 3
Requires-Dist: Pillow
Requires-Dist: click
